setup.py
probability_and_distribution/Binomialdistribution.py
probability_and_distribution/Gaussiandistribution.py
probability_and_distribution/Generaldistribution.py
probability_and_distribution/__init__.py
probability_and_distribution.egg-info/PKG-INFO
probability_and_distribution.egg-info/SOURCES.txt
probability_and_distribution.egg-info/dependency_links.txt
probability_and_distribution.egg-info/not-zip-safe
probability_and_distribution.egg-info/top_level.txt