Metadata-Version: 1.0
Name: probability-and-distribution
Version: 0.2
Summary: Probability and distributions
Home-page: UNKNOWN
Author: UNKNOWN
Author-email: UNKNOWN
License: UNKNOWN
Platform: UNKNOWN
